d2/__init__.py
d2/config.py
d2/fence.py
d2/img.py
d2/plugin.py
d2/css/__init__.py
d2/css/mkdocs_d2_plugin.css
mkdocs_d2_plugin-1.6.0.dist-info/LICENSE
mkdocs_d2_plugin-1.6.0.dist-info/METADATA
mkdocs_d2_plugin-1.6.0.dist-info/WHEEL
mkdocs_d2_plugin-1.6.0.dist-info/entry_points.txt
mkdocs_d2_plugin-1.6.0.dist-info/top_level.txt
mkdocs_d2_plugin-1.6.0.dist-info/RECORD
