Metadata-Version: 2.1
Name: mkdocs-d2-plugin
Version: 1.6.0
Summary: MkDocs plugin for D2
Home-page: https://github.com/landmaj/mkdocs-d2-plugin
Author: Michał Wieluński
Author-email: michal@wielunski.net
License: MIT
Keywords: mkdocs python markdown d2 diagram
Classifier: Development Status :: 5 - Production/Stable
Classifier: Intended Audience :: Developers
Classifier: Intended Audience :: Information Technology
Classifier: Intended Audience :: Science/Research
Classifier: License :: OSI Approved :: MIT License
Classifier: Programming Language :: Python
Classifier: Programming Language :: Python :: 3 :: Only
Classifier: Programming Language :: Python :: 3.9
Classifier: Programming Language :: Python :: 3.10
Classifier: Programming Language :: Python :: 3.11
Classifier: Programming Language :: Python :: 3.12
Requires-Python: >=3.9
License-File: LICENSE
Requires-Dist: mkdocs>=1.6.0
Requires-Dist: pymdown-extensions>=9.0
Requires-Dist: pydantic>=2.0
Requires-Dist: packaging
